{
  "name": "Bernice Wise",
  "age": 65,
  "address": {
    "street": "Misom Loop",
    "city": "Laziuvi",
    "state": "NY",
    "zip": "78533"
  },
  "contact": {
    "phone": "(518) 376-3727",
    "servicePhone": "800741872"
  },
  "birthday": "2006-05-17T17:19:39.259Z",
  "ip": "148.48.214.94",
  "foo": "bar",
  "profile": {
    "about": "Jilaflad linhilew midko kawzog owkuwkih ru ebojueba konevgo me fufak solzebeke we geni iksak. Coc zavomu pu pejmaf osuejesin gobgo vowvuna anivawsil zab sut uwhefzel cebmo se jabdof bo. Wumhavak zawidop bu egbafoh ocva ti gi raztedku surzo runkeju supil huk selekvi ah. Popza ketpo su buipopi wuraoga fuppi ekisudih rozek matnud duhtasbac heki zaz ajiud. Wu alelorota be keemged zo bof jopfe zep ulazen boprew visvek unola collasinu vu vub codcobli jo. Fonow keiw ib teij an mev uje mimo nuiz ni ak katpivcil gu uwasuot. Het pa kiwa kokusa sitinti ewcu undehal gu lidicuga vi fiud dot.",
    "bio": "Tuule guowa bapul ceher naco aka jekvel zawcursab sovhih fud biwiro wed safudih guwvuzi if. Baggecit zi bespanem libof funu udjulan gamozbok lohauj bo gemfero veut zibne nobvowop se agos lilmor wauh. Toniuw tim im kis tejna tewa dug ge zumota wuh mu cesesit fac dinukib."
  },
  "apiKey": "e3c011eea315c265686e567213db57865547fc8690ae8378c709d9f0a3234eee",
  "currency": {
    "code": "SCR",
    "name": "Seychelles Rupee"
  }
}