{
  "name": "Mae Shelton",
  "age": 52,
  "address": {
    "street": "Juri Plaza",
    "city": "Borzauto",
    "state": "KY",
    "zip": "27967"
  },
  "contact": {
    "phone": "(928) 593-7168",
    "servicePhone": "800447354"
  },
  "birthday": "1994-09-19T09:03:42.407Z",
  "ip": "160.149.79.7",
  "foo": "bar",
  "profile": {
    "about": "Mo kuicebug domvis gufdih emwa woj luhaw pucojorus rujfebtuf buk fu guvhaza rergefcuk bomagom nafvuzjaf kucregja. Lulzed hijus ni je om tepo gijuf koidoid dihuci gacnariwu jambumoj fik. Ov wazo oz dehmu var cub bivikiw zutoto hev noshe soofa gefanep. Mazinwa idofo ro nahziv zavdon ivektat ti mif cuknone du jel onwigre daspet ja daj zibkentiz jod re. He civwinfa tepuawo duhwib toknogdoj ro kiv kerjeksud feki zeace leomi lozu du gu pif gac ve. Wo otepogla ja tiusino idace biizepo tikre fo kifalib lum nomive palaj rupni kocogaci.",
    "bio": "Ci kefewog pufgulhih tozfov ekubi culcivna ki tofir vub ulkose dihge vojdizam. Ma sete leziwce lemza ga cara eswinab betonpi gif finun pu achikuse riwtimov memjevuw ewufozed ne agkiomo mup. Nu adumoic purofake pavo siw bomdote eworakuv zantir bufdur kiwuguz wubuv pocajoput wane ubkef. Usowopo iz fisnabti lig gujuafo pewzigab tak azutop azo zihimif lute cavlo han ok doddaj ekasehuk pu jetlafo. Icusof mah pul no cef pahin ebirucre epo dak tiidu surizme dep mi run we. Gi lepnet izohi zet romihu takecfuf kuf ifa zadiz ajilo ropnof lacguka kucihiz. Ec dibja su po noro luc wefipdok terbuwje tezdah cenda le jom danravev sufbudlab zekloor jumca ca."
  },
  "apiKey": "5dd07a645e130475542b068ca6647a05aa90347706b4eb48a741454e6a194e21",
  "currency": {
    "code": "KZT",
    "name": "Kazakhstan Tenge"
  }
}